botinfrastructure
chimera
examples
humanlike-automation-mcp
humanlike_automation
venv
venv_new
