Metadata-Version: 2.4
Name: humanlike-automation
Version: 1.0.0
Summary: Human-like browser automation with stealth capabilities and anti-detection features
Author-email: Human-like Automation Team <contact@humanlikeautomation.com>
License: MIT
Project-URL: Homepage, https://github.com/humanlike-automation/humanlike-automation
Project-URL: Documentation, https://github.com/humanlike-automation/humanlike-automation#readme
Project-URL: Repository, https://github.com/humanlike-automation/humanlike-automation
Project-URL: Bug Tracker, https://github.com/humanlike-automation/humanlike-automation/issues
Project-URL: Examples, https://github.com/humanlike-automation/humanlike-automation/tree/main/examples
Keywords: selenium,automation,browser,stealth,anti-detection,web-scraping,humanlike,undetected,chrome,webdriver,bot,crawler,testing,web-automation,bypass-detection
Classifier: Development Status :: 4 - Beta
Classifier: Intended Audience :: Developers
Classifier: Topic :: Software Development :: Testing
Classifier: Topic :: Software Development :: Libraries :: Python Modules
Classifier: Topic :: Internet :: WWW/HTTP :: Browsers
Classifier: License :: OSI Approved :: MIT License
Classifier: Programming Language :: Python :: 3
Classifier: Programming Language :: Python :: 3.7
Classifier: Programming Language :: Python :: 3.8
Classifier: Programming Language :: Python :: 3.9
Classifier: Programming Language :: Python :: 3.10
Classifier: Programming Language :: Python :: 3.11
Classifier: Programming Language :: Python :: 3.12
Classifier: Operating System :: OS Independent
Classifier: Environment :: Web Environment
Requires-Python: >=3.7
License-File: LICENSE
Requires-Dist: selenium>=4.33.0
Requires-Dist: undetected-chromedriver>=3.5.5
Requires-Dist: webdriver-manager>=4.0.2
Requires-Dist: fake-useragent>=2.2.0
Requires-Dist: pyperclip>=1.9.0
Requires-Dist: requests>=2.32.4
Requires-Dist: beautifulsoup4>=4.13.4
Requires-Dist: python-dotenv>=1.0.0
Requires-Dist: urllib3>=1.26.0
Requires-Dist: psutil>=5.9.0
Requires-Dist: fastapi>=0.115.14
Requires-Dist: uvicorn>=0.35.0
Provides-Extra: dev
Requires-Dist: pytest>=6.0; extra == "dev"
Requires-Dist: pytest-cov>=2.0; extra == "dev"
Requires-Dist: black>=21.0; extra == "dev"
Requires-Dist: flake8>=3.8; extra == "dev"
Requires-Dist: mypy>=0.800; extra == "dev"
Provides-Extra: docs
Requires-Dist: sphinx>=4.0; extra == "docs"
Requires-Dist: sphinx-rtd-theme>=0.5; extra == "docs"
Provides-Extra: stealth
Requires-Dist: undetected-chromedriver>=3.5.0; extra == "stealth"
Requires-Dist: selenium-stealth>=1.0.6; extra == "stealth"
Dynamic: license-file
